distance/__init__.py
distance/__main__.py
distance/_argtaker.py
distance/_autoload_gen.py
distance/_common.py
distance/_core.py
distance/_data.py
distance/_level.py
distance/_nonlevel.py
distance/_version.py
distance/base.py
distance/bytes.py
distance/classes.py
distance/constants.py
distance/construct.py
distance/lazy.py
distance/levelobjects.py
distance/printing.py
distance/transform.py
distance/_autoload/__init__.py
distance/_autoload/_classes.py
distance/_impl/__init__.py
distance/_impl/fragments/__init__.py
distance/_impl/fragments/bases.py
distance/_impl/fragments/group.py
distance/_impl/fragments/info.py
distance/_impl/fragments/leaderboard.py
distance/_impl/fragments/levelfragments.py
distance/_impl/fragments/levelinfos.py
distance/_impl/fragments/levelsettings.py
distance/_impl/fragments/npfragments.py
distance/_impl/fragments/profileprogress.py
distance/_impl/fragments/replay.py
distance/_impl/fragments/setabilitiestrigger.py
distance/_impl/fragments/warpanchor.py
distance/_impl/fragments/workshoplevelinfos.py
distance/_impl/level_content/__init__.py
distance/_impl/level_content/layer.py
distance/_impl/level_content/levelsettings_base.py
distance/_impl/level_content/newlevelsettings.py
distance/_impl/level_content/oldlevelsettings.py
distance/_impl/level_objects/__init__.py
distance/_impl/level_objects/group.py
distance/_impl/level_objects/objects.py
distance/filter/__init__.py
distance/filter/base.py
distance/filter/downgrade.py
distance/filter/goldify.py
distance/filter/remove.py
distance/filter/settings.py
distance/filter/unkill.py
distance/filter/visualize.py
distance_scripts/__init__.py
distance_scripts/_common.py
distance_scripts/bytes.py
distance_scripts/filterlevel.py
distance_scripts/groupobjects.py
distance_scripts/mkcustomobject.py
distance_scripts/mklevelinfos.py
distance_scripts/mktriangles.py
distance_scripts/objtobytes.py
distance_scripts/querymaps.py
distanceutils-0.5.1.dist-info/METADATA
distanceutils-0.5.1.dist-info/RECORD
distanceutils-0.5.1.dist-info/WHEEL
distanceutils-0.5.1.dist-info/entry_points.txt
distanceutils-0.5.1.dist-info/top_level.txt
