Metadata-Version: 2.1
Name: distanceutils
Version: 0.5.1
Summary: Read and modify .bytes files of the Refract Studios game Distance
Home-page: https://gitlab.com/ferreum/distanceutils
Author: UNKNOWN
Author-email: code.danielk@gmail.com
License: MIT
Keywords: distance game bytes file level map read edit modify
Platform: UNKNOWN
Classifier: Development Status :: 3 - Alpha
Classifier: Intended Audience :: Developers
Classifier: License :: OSI Approved :: MIT License
Classifier: Natural Language :: English
Classifier: Operating System :: OS Independent
Classifier: Programming Language :: Python :: 3.5
Classifier: Programming Language :: Python :: 3.6
Classifier: Programming Language :: Python :: 3.7
Requires-Dist: construct (<3.0,>=2.9)
Requires-Dist: numpy (<2.0,>=1.13.3)
Requires-Dist: numpy-quaternion (>=2017.10.19)
Requires-Dist: trampoline
